{
  "main": {
    "id": "67ba9a98be54d91a",
    "type": "split",
    "children": [
      {
        "id": "d8aa9c69e26be401",
        "type": "tabs",
        "children": [
          {
            "id": "b1d94d000b933ce6",
            "type": "leaf",
            "state": {
              "type": "markdown",
              "state": {
                "file": "econ & pol/Ökosystemdienstleistungen.md",
                "mode": "source",
                "source": true
              },
              "icon": "lucide-file",
              "title": "Ökosystemdienstleistungen"
            }
          },
          {
            "id": "e4e9f706afac1bb9",
            "type": "leaf",
            "state": {
              "type": "markdown",
              "state": {
                "file": "econ & pol/Ökosystemdienstleistungen.md",
                "mode": "source",
                "source": true
              },
              "icon": "lucide-file",
              "title": "Ökosystemdienstleistungen"
            }
          },
          {
            "id": "32c1a67940832fb3",
            "type": "leaf",
            "state": {
              "type": "markdown",
              "state": {
                "file": "bio/Biogeochemie/Wurzeln.md",
                "mode": "source",
                "source": true
              },
              "icon": "lucide-file",
              "title": "Wurzeln"
            }
          }
        ],
        "currentTab": 2
      }
    ],
    "direction": "vertical"
  },
  "left": {
    "id": "5c70e352f118db3e",
    "type": "split",
    "children": [
      {
        "id": "4c711e634aa712ef",
        "type": "tabs",
        "children": [
          {
            "id": "54129478d09a05ea",
            "type": "leaf",
            "state": {
              "type": "file-explorer",
              "state": {
                "sortOrder": "alphabetical"
              },
              "icon": "lucide-folder-closed",
              "title": "Files"
            }
          },
          {
            "id": "ebf5bee386dd0e5e",
            "type": "leaf",
            "state": {
              "type": "search",
              "state": {
                "query": "Mikroklima",
                "matchingCase": false,
                "explainSearch": false,
                "collapseAll": true,
                "extraContext": false,
                "sortOrder": "alphabetical"
              },
              "icon": "lucide-search",
              "title": "Search"
            }
          },
          {
            "id": "dcf49c1161dff5c3",
            "type": "leaf",
            "state": {
              "type": "bookmarks",
              "state": {},
              "icon": "lucide-bookmark",
              "title": "Bookmarks"
            }
          }
        ]
      }
    ],
    "direction": "horizontal",
    "width": 200
  },
  "right": {
    "id": "068dc6cf241ee037",
    "type": "split",
    "children": [
      {
        "id": "e4f254566fd7cff9",
        "type": "tabs",
        "children": [
          {
            "id": "740f480654be1575",
            "type": "leaf",
            "state": {
              "type": "backlink",
              "state": {
                "file": "bio/Biogeochemie/Wurzeln.md",
                "collapseAll": true,
                "extraContext": true,
                "sortOrder": "alphabetical",
                "showSearch": true,
                "searchQuery": "",
                "backlinkCollapsed": false,
                "unlinkedCollapsed": true
              },
              "icon": "links-coming-in",
              "title": "Backlinks for Wurzeln"
            }
          },
          {
            "id": "a303bf3a33038dc2",
            "type": "leaf",
            "state": {
              "type": "advanced-tables-toolbar",
              "state": {},
              "icon": "spreadsheet",
              "title": "Advanced Tables"
            }
          }
        ]
      }
    ],
    "direction": "horizontal",
    "width": 200
  },
  "left-ribbon": {
    "hiddenItems": {
      "table-editor-obsidian:Advanced Tables Toolbar": false,
      "switcher:Open quick switcher": false,
      "graph:Open graph view": false,
      "canvas:Create new canvas": false,
      "command-palette:Open command palette": false,
      "markdown-importer:Open format converter": false,
      "templater-obsidian:Templater": false,
      "obsidian-to-anki-plugin:Obsidian_to_Anki - Scan Vault": false
    }
  },
  "active": "32c1a67940832fb3",
  "lastOpenFiles": [
    "bio/Biogeochemie/Aufbau des Edaphons.md",
    "bio/Biogeochemie/Wurzeln.md",
    "Attachments/{E8E881DE-3E69-43EF-B111-2794FEC8455B}.png",
    "Overview Files/Overview Biogeochemie.md",
    "geoöko/Biogeo/Abholzung.md",
    "Overview Files/Overview Physische Geographie, Geoökologie.md",
    "geoöko/Stoffkreisläufe und Haushalte.md",
    "bio/Geobotanik/Landschaftsökologie.md",
    "Overview Files/Overview Gesteinsbestimmung.md",
    "Overview Files/Overview Geodynamik.md",
    "Overview Files/Overview Geobotanik.md",
    "Overview Files/Overview Geo-Basics.md",
    "Overview Files/Overview Definitionen Mineralogie.md",
    "Overview Files/Overview Chemie Grundlagen.md",
    "bio/Biogeochemie/Ökosysteme.md",
    "bio/Biogeochemie/Molekularbiologische Methoden.md",
    "bio/Biogeochemie/Ernährungsformen von Organismen.md",
    "bio/Biogeochemie/Bodenflora.md",
    "bio/Biogeochemie/Bodenfauna.md",
    "bio/Biogeochemie/Boden als Habitat.md",
    "bio/Biogeochemie/Black Carbon.md",
    "bio/Biogeochemie/Biogeochemie Einführung.md",
    "bio/Biogeochemie/Biochemische Methoden.md",
    "bio/Biogeochemie/Pilze.md",
    "bio/Biogeochemie/Bakterien.md",
    "bio/Biogeochemie/Algen.md",
    "bio/Biogeochemie/Arthropoden.md",
    "Attachments/{B9B99D40-F429-419B-9FB4-B3136F725DCD}.png",
    "Attachments/{B66F4F3D-CE23-42E0-BA01-34E9AE7541B7}.png",
    "Attachments/{D1721342-B235-4423-8621-EF8FC7976532}.png",
    "Attachments/{07599F88-2545-46A6-935E-DFDB1A44281A}.png",
    "Attachments/{86A27236-6AB3-4FC7-9679-0470E34B93FF}.png",
    "Attachments/{C0936A5E-38A3-4DF5-88FA-4D50AB0A3C5F}.png",
    "Attachments/{9709E241-6AA2-494A-997E-2D749C90BF82}.png",
    "Attachments/{8218A800-C00D-4EAA-966D-50AEA4897281}.png",
    "Attachments/{9A39F120-E41D-42B9-9F36-B4ED20E73FF7}.png",
    "geo/Bodenkunde",
    "bio/Biogeochemie",
    "Untitled",
    "econ & pol",
    "Physik",
    "geo/Hydrogeologie",
    "preamble.sty.bak",
    "preamble.sty",
    "chem/Chemie Grundlagen",
    "bio/Tierökologie",
    "Untitled.canvas"
  ]
}